gencov_io/__init__.py
gencov_io-0.0.14.dist-info/METADATA
gencov_io-0.0.14.dist-info/WHEEL
gencov_io-0.0.14.dist-info/licenses/LICENSE
gencov_io-0.0.14.dist-info/RECORD
